AUTHORS
ChangeLog
LICENSE
README.md
requirements.txt
setup.cfg
setup.py
qhanutils/__init__.py
qhanutils/logger.py
qhanutils/timer.py
qhanutils.egg-info/PKG-INFO
qhanutils.egg-info/SOURCES.txt
qhanutils.egg-info/dependency_links.txt
qhanutils.egg-info/not-zip-safe
qhanutils.egg-info/pbr.json
qhanutils.egg-info/requires.txt
qhanutils.egg-info/top_level.txt
tests/test.py