Metadata-Version: 2.1
Name: qhanutils
Version: 0.0.2
Summary: "qhan's personal utilities"
Home-page: UNKNOWN
License: UNKNOWN
Platform: UNKNOWN
